sizestr/__init__.py
sizestr/py.typed
sizestr-1.2.1.dist-info/METADATA
sizestr-1.2.1.dist-info/WHEEL
sizestr-1.2.1.dist-info/licenses/LICENSE
sizestr-1.2.1.dist-info/RECORD
