Metadata-Version: 2.4
Name: sizestr
Version: 1.2.1
Summary: Simple and fast formatting of sizes for Python
Project-URL: Issues, https://github.com/Zaczero/sizestr/issues
Project-URL: Repository, https://github.com/Zaczero/sizestr
Author-email: Kamil Monicz <kamil@monicz.dev>
License-Expression: 0BSD
License-File: LICENSE
Keywords: file-size,human-readable,humanize,stringify
Classifier: Development Status :: 5 - Production/Stable
Classifier: Intended Audience :: Developers
Classifier: License :: OSI Approved :: Zero-Clause BSD (0BSD)
Classifier: Operating System :: OS Independent
Classifier: Programming Language :: Python :: 3.9
Classifier: Programming Language :: Python :: 3.10
Classifier: Programming Language :: Python :: 3.11
Classifier: Programming Language :: Python :: 3.12
Classifier: Programming Language :: Python :: 3.13
Classifier: Topic :: Software Development :: Libraries :: Python Modules
Classifier: Typing :: Typed
Requires-Python: >=3.9
